openslides/__init__.py
openslides/__main__.py
openslides/asgi.py
openslides/global_settings.py
openslides/routing.py
openslides/urls.py
openslides/agenda/__init__.py
openslides/agenda/access_permissions.py
openslides/agenda/apps.py
openslides/agenda/config_variables.py
openslides/agenda/models.py
openslides/agenda/projector.py
openslides/agenda/serializers.py
openslides/agenda/signals.py
openslides/agenda/urls.py
openslides/agenda/views.py
openslides/agenda/migrations/0001_initial.py
openslides/agenda/migrations/0002_item_duration.py
openslides/agenda/migrations/0003_auto_20170818_1202.py
openslides/agenda/migrations/0004_speaker_marked.py
openslides/agenda/migrations/0005_auto_20180815_1109.py
openslides/agenda/migrations/__init__.py
openslides/agenda/static/css/agenda/_list_of_speakers.scss
openslides/agenda/static/css/agenda/_projector.scss
openslides/agenda/static/css/agenda/_site.scss
openslides/agenda/static/js/agenda/base.js
openslides/agenda/static/js/agenda/csv.js
openslides/agenda/static/js/agenda/docx.js
openslides/agenda/static/js/agenda/pdf.js
openslides/agenda/static/js/agenda/projector.js
openslides/agenda/static/js/agenda/site.js
openslides/agenda/static/templates/agenda/current-list-of-speakers.html
openslides/agenda/static/templates/agenda/item-detail.html
openslides/agenda/static/templates/agenda/item-list.html
openslides/agenda/static/templates/agenda/item-sort.html
openslides/agenda/static/templates/agenda/list-of-speakers-partial-management.html
openslides/agenda/static/templates/agenda/partial-slide-current-list-of-speakers-overlay.html
openslides/agenda/static/templates/agenda/partial-slide-current-list-of-speakers.html
openslides/agenda/static/templates/agenda/slide-current-list-of-speakers.html
openslides/agenda/static/templates/agenda/slide-item-list.html
openslides/agenda/static/templates/agenda/slide-list-of-speakers.html
openslides/agenda/static/templates/docx/agenda.docx
openslides-2.3.dist-info/METADATA
openslides-2.3.dist-info/RECORD
openslides-2.3.dist-info/WHEEL
openslides-2.3.dist-info/entry_points.txt
openslides-2.3.dist-info/top_level.txt
