Metadata-Version: 2.1
Name: openslides
Version: 2.3
Summary: Presentation and assembly system
Home-page: https://openslides.org
Author: OpenSlides Team <support@openslides.org>
Author-email: support@openslides.org
License: MIT
Platform: UNKNOWN
Classifier: Development Status :: 5 - Production/Stable
Classifier: Environment :: Web Environment
Classifier: Framework :: Django
Classifier: License :: OSI Approved :: MIT License
Classifier: Operating System :: OS Independent
Classifier: Programming Language :: Python :: 3.5
Classifier: Programming Language :: Python :: 3.6
Classifier: Programming Language :: Python :: 3.7
Requires-Dist: bleach (<2.2,>=1.5.0)
Requires-Dist: channels (<1.2,>=1.1)
Requires-Dist: daphne (<2)
Requires-Dist: Django (<2.2,>=1.10.4)
Requires-Dist: djangorestframework (<3.9,>=3.4)
Requires-Dist: jsonfield2 (<3.1,>=3.0)
Requires-Dist: mypy-extensions (<0.4,>=0.3)
Requires-Dist: PyPDF2 (<1.27,>=1.26)
Requires-Dist: roman (<3.1,>=2.0)
Requires-Dist: setuptools (<41.0,>=29.0)
